README.txt
setup.py
VarEvents/__init__.py
VarEvents.egg-info/PKG-INFO
VarEvents.egg-info/SOURCES.txt
VarEvents.egg-info/dependency_links.txt
VarEvents.egg-info/not-zip-safe
VarEvents.egg-info/top_level.txt