Metadata-Version: 1.1
Name: VarEvents
Version: 1.0.0
Summary: Python module to create variables that can raise custom events.
Home-page: http://automic.us/projects/pyisy
Author: Ryan Kraus
Author-email: automicus@gmail.com
License: Apache License 2.0
Download-URL: https://github.com/automicus/varevents/tarball/1.0.1
Keywords: event
Platform: any
Classifier: Intended Audience :: Developers
Classifier: License :: OSI Approved :: Apache Software License
Classifier: Operating System :: OS Independent
Classifier: Programming Language :: Python
Classifier: Programming Language :: Python :: 2
Classifier: Programming Language :: Python :: 3
Classifier: Topic :: Software Development :: Libraries :: Python Modules
